{
  "db_name": "PostgreSQL",
  "query": "\n        SELECT id, token_hash\n        FROM bot_applications\n        WHERE bot_user_id = $1 AND token_hash IS NOT NULL\n        ",
  "describe": {
    "columns": [
      {
        "ordinal": 0,
        "name": "id",
        "type_info": "Uuid"
      },
      {
        "ordinal": 1,
        "name": "token_hash",
        "type_info": "Text"
      }
    ],
    "parameters": {
      "Left": [
        "Uuid"
      ]
    },
    "nullable": [
      false,
      true
    ]
  },
  "hash": "76062a919b17d4118b602211bf3fc13759b184a078955e50596352687475dfe8"
}
